py_rust_stemmers_tuned-0.1.9.dist-info/METADATA
py_rust_stemmers_tuned-0.1.9.dist-info/WHEEL
py_rust_stemmers_tuned-0.1.9.dist-info/licenses/LICENSE
py_rust_stemmers_tuned/__init__.py
py_rust_stemmers_tuned/__init__.pyi
py_rust_stemmers_tuned/py.typed
py_rust_stemmers_tuned/py_rust_stemmers_tuned.cpython-314t-darwin.so
py_rust_stemmers_tuned-0.1.9.dist-info/RECORD
