Metadata-Version: 2.4
Name: py_rust_stemmers_tuned
Version: 0.1.9
License-File: LICENSE
Summary: Fast and parallel snowball stemmer
Requires-Python: >=3.14
